src/main/__init__.py
src/main/display/display.py
src/main/pandas/pandas.py
hmcalisterhopfieldutils-0.0.1.dist-info/METADATA
hmcalisterhopfieldutils-0.0.1.dist-info/WHEEL
hmcalisterhopfieldutils-0.0.1.dist-info/licenses/LICENSE
hmcalisterhopfieldutils-0.0.1.dist-info/RECORD
